ybxiehaode/__init__.py
ybxiehaode/main.py
ybxiehaode-0.1.0.dist-info/METADATA
ybxiehaode-0.1.0.dist-info/WHEEL
ybxiehaode-0.1.0.dist-info/entry_points.txt
ybxiehaode-0.1.0.dist-info/top_level.txt
ybxiehaode-0.1.0.dist-info/RECORD
